hatch_openzim/__about__.py
hatch_openzim/__init__.py
hatch_openzim/build_hook.py
hatch_openzim/files_install.py
hatch_openzim/hooks.py
hatch_openzim/metadata.py
hatch_openzim/metadata_hook.py
hatch_openzim/shared.py
hatch_openzim/utils.py
hatch_openzim-0.2.4.dist-info/METADATA
hatch_openzim-0.2.4.dist-info/WHEEL
hatch_openzim-0.2.4.dist-info/entry_points.txt
hatch_openzim-0.2.4.dist-info/licenses/LICENSE
hatch_openzim-0.2.4.dist-info/RECORD
