Metadata-Version: 2.4
Name: hatch-openzim
Version: 0.2.4
Summary: openZIM hatch plugin to set metadata automatically and download files at build time
Project-URL: Donate, https://www.kiwix.org/en/support-us/
Project-URL: Homepage, https://github.com/openzim/hatch-openzim
Author-email: openZIM <dev@openzim.org>
License: GPL-3.0-or-later
License-File: LICENSE
Keywords: download,file,hatch,plugin
Classifier: Framework :: Hatch
Classifier: License :: OSI Approved :: GNU General Public License v3 or later (GPLv3+)
Classifier: Programming Language :: Python :: 3
Classifier: Programming Language :: Python :: 3.10
Classifier: Programming Language :: Python :: 3.11
Classifier: Programming Language :: Python :: 3.12
Classifier: Programming Language :: Python :: 3.13
Classifier: Programming Language :: Python :: 3.14
Requires-Python: <3.15,>=3.10
Requires-Dist: hatchling<2,>=1.27.0
Requires-Dist: packaging<26,>=24.2
Requires-Dist: toml>=0.10
Provides-Extra: check
Requires-Dist: pyright==1.1.407; extra == 'check'
Provides-Extra: dev
Requires-Dist: black==25.9.0; extra == 'dev'
Requires-Dist: coverage==7.11.0; extra == 'dev'
Requires-Dist: debugpy==1.8.17; extra == 'dev'
Requires-Dist: invoke==2.2.1; extra == 'dev'
Requires-Dist: pre-commit==4.3.0; extra == 'dev'
Requires-Dist: pyright==1.1.407; extra == 'dev'
Requires-Dist: pytest==8.4.2; extra == 'dev'
Requires-Dist: ruff==0.14.3; extra == 'dev'
Provides-Extra: lint
Requires-Dist: black==25.9.0; extra == 'lint'
Requires-Dist: ruff==0.14.3; extra == 'lint'
Provides-Extra: scripts
Requires-Dist: invoke==2.2.1; extra == 'scripts'
Provides-Extra: test
Requires-Dist: coverage==7.11.0; extra == 'test'
Requires-Dist: pytest==8.4.2; extra == 'test'
